{
  "id": "164c5ac69a18",
  "type": "finding",
  "topic": "VIX Jan 19-30 2026 max high forecast",
  "summary": "Current VIX ~14.5, period includes likely FOMC meeting (Jan 27-28) and Q4 earnings season. Monte Carlo gives median max high ~17.5-19.",
  "content": "Key findings:\n- Current VIX: 14.51 (close Jan 2, 2026), high of 15.42 on Jan 2\n- VIX has been declining from ~28 in late Nov to ~14.5 currently\n- Recent calm 9-day windows (Dec 22-Jan 2): max high 15.42\n- More active 9-day windows (Dec 8-19): max high 18.00\n- FOMC meeting likely Jan 27-28 (within window) - major catalyst\n- Q4 earnings season starts late January - another catalyst\n- Jan 19 is MLK Day (market closed), so 9 trading days in window\n- Monte Carlo simulation (with jumps, FOMC effects): median ~17.5-19, 90th ~22-26\n- Historical VIX max highs over 2-week periods from ~14.5 base: typically 16-20 in calm conditions",
  "sources": [
    "Yahoo Finance VIX data"
  ],
  "confidence": 0.7,
  "question_id": 41067,
  "report_path": "",
  "created_at": "2026-02-07T06:33:10.794007Z"
}