{
  "slug": "russia-annual-gdp-growth-rate-recent-quarters-2025-1adebf7f",
  "query": "Russia annual GDP growth rate recent quarters 2025 and Q1 2026, what is the trajectory and latest official figures from Rosstat and Trading Economics",
  "answer": "Research complete. Here's the summary:\n\n**Russia GDP Growth \u2014 Trajectory and Latest Official Figures**\n\nThe clear trend is a sharp, steady deceleration through 2025 that tipped into contraction in Q1 2026:\n\n- **Q1 2026: \u22120.2% YoY** (Rosstat-confirmed ~June 17, 2026) \u2014 the **first annual contraction since Q1 2023**, reversing +1.0% in Q4 2025. Led by manufacturing (\u22121.5%), professional/scientific/technical (\u22126.1%), and transport (\u22121.8%).\n- **2025 quarterly path:** Q1 +1.4% \u2192 Q2 +1.1% \u2192 Q3 +0.6% \u2192 implied Q4 ~+1.0%\n- **Full-year 2025: +1.0%** (Rosstat-confirmed), a steep fall from **+4.9% in 2024**.\n\n**Official forward positions (context only):** The Russian government downgraded its 2026 forecast to **0.4%** (from 1.3%); the CBR maintains a **0.5%\u20131.5%** range for 2026. BOFIT notes a partial rebound in early-Q2 2026 (~+2% YoY core-sector index in Mar\u2013Apr; ministry estimated ~1.3% GDP growth in April), suggesting stabilization after the weak start.\n\n**Sourcing notes:** Figures come primarily from Rosstat as reported via Trading Economics, TASS, and Interfax, cross-checked against BOFIT, Worldometer, and The Bell. The World Bank API did not return the Russia GDP-growth series (404 error), so that source couldn't be used for cross-validation.",
  "sources": [
    {
      "url": "https://tradingeconomics.com/russia/gdp-growth-annual",
      "title": "Russia GDP Annual Growth Rate",
      "domain": "tradingeconomics.com",
      "accessed_at": "2026-07-08T00:00:00Z",
      "snippet": "Russian GDP contracted by 0.2% YoY in Q1 2026, confirming the first annual decline since Q1 2023."
    },
    {
      "url": "https://tradingeconomics.com/russia/gdp-growth-annual/news/551263",
      "title": "Russia GDP Contracts in Q1",
      "domain": "tradingeconomics.com",
      "accessed_at": "2026-07-08T00:00:00Z",
      "snippet": "Russia's economy contracted 0.2% YoY in Q1 2026, first decline in three years, reversing 1% expansion in prior quarter; government downgraded full-year forecast to 0.4% from 1.3%."
    },
    {
      "url": "https://tradingeconomics.com/russia/gdp-growth-annual/news/463949",
      "title": "Russian GDP Growth Confirmed at 1.4%",
      "domain": "tradingeconomics.com",
      "accessed_at": "2026-07-08T00:00:00Z",
      "snippet": "Russia's GDP grew 1.4% in Q1 2025, in line with preliminary estimate, slowest since Q2 2023."
    },
    {
      "url": "https://tradingeconomics.com/russia/gdp-growth-annual/news/509655",
      "title": "Russian GDP Growth Confirmed at 0.6%",
      "domain": "tradingeconomics.com",
      "accessed_at": "2026-07-08T00:00:00Z",
      "snippet": "Russia's GDP grew 0.6% YoY in Q3 2025, weakest since 2023, slowing from 1.1% in Q2."
    },
    {
      "url": "https://tradingeconomics.com/russia/full-year-gdp-growth",
      "title": "Russia Full Year GDP Growth",
      "domain": "tradingeconomics.com",
      "accessed_at": "2026-07-08T00:00:00Z",
      "snippet": "Russian GDP expanded 1% in 2025, a slowdown from 4.9% in 2024."
    },
    {
      "url": "https://tass.com/economy/2001933",
      "title": "Rosstat preliminarily estimates Russia's GDP growth in Q2 2025 at 1.1%",
      "domain": "tass.com",
      "accessed_at": "2026-07-08T00:00:00Z",
      "snippet": "Russia's GDP growth was 1.1% YoY in Q2 2025 (preliminary); Q1 2025 confirmed at 1.4%."
    },
    {
      "url": "https://tass.com/economy/2023817",
      "title": "Russia's GDP reaches $1.193 trillion in 1H 2025",
      "domain": "tass.com",
      "accessed_at": "2026-07-08T00:00:00Z",
      "snippet": "Rosstat confirmed H1 2025 GDP growth at 1.2%; Q2 2025 provisionally 1.1%."
    },
    {
      "url": "https://interfax.com/newsroom/top-stories/117073/",
      "title": "Rosstat confirms estimate that Russia's GDP grew 1.0% in 2025",
      "domain": "interfax.com",
      "accessed_at": "2026-07-08T00:00:00Z",
      "snippet": "Rosstat confirmed 2025 full-year GDP growth at 1.0%."
    },
    {
      "url": "https://www.bofit.fi/en/monitoring/weekly/2026/vw202623_1/",
      "title": "Russian economy stabilising after weak start of the year",
      "domain": "bofit.fi",
      "accessed_at": "2026-07-08T00:00:00Z",
      "snippet": "Core-sector index grew ~2% YoY in Mar-Apr 2026 vs ~-3% in Jan-Feb; ministry estimated GDP grew 1.3% YoY in April 2026."
    },
    {
      "url": "https://interfax.com/newsroom/top-stories/117307/",
      "title": "Central Bank maintains forecast for Russia's GDP growth in 2026 at 0.5%-1.5%",
      "domain": "interfax.com",
      "accessed_at": "2026-07-08T00:00:00Z",
      "snippet": "CBR maintains 2026 GDP forecast at 0.5%-1.5% and 2027 at 1.5%-2.5%."
    },
    {
      "url": "https://en.thebell.io/gdp-data-what-it-reveals-what-it-conceals/",
      "title": "GDP data \u2014 what it reveals, what it conceals",
      "domain": "thebell.io",
      "accessed_at": "2026-07-08T00:00:00Z",
      "snippet": "Rosstat reported 1% growth in 2025 and revised 2024 up to 4.9% and 2023 to 4.1%."
    },
    {
      "url": "https://www.worldometers.info/gdp/russia-gdp/",
      "title": "Russia GDP (2026) - Worldometer",
      "domain": "worldometers.info",
      "accessed_at": "2026-07-08T00:00:00Z",
      "snippet": "2025 GDP growth 1.0%, 2024 4.9%, 2023 4.1%, 2022 -1.4%."
    }
  ],
  "key_facts": [
    "Q1 2026 Russia GDP: \u22120.2% YoY (Rosstat-confirmed ~2026-06-17), first annual contraction since Q1 2023, reversing +1.0% in Q4 2025",
    "Full-year 2025 GDP growth confirmed at +1.0% by Rosstat, down sharply from +4.9% in 2024",
    "Q1 2025: +1.4% YoY (confirmed 2025-06-18), slowest since expansion resumed in Q2 2023",
    "Q2 2025: +1.1% YoY preliminary; H1 2025 growth = +1.2%",
    "Q3 2025: +0.6% YoY (confirmed 2025-12-12), weakest pace since 2023",
    "Q1 2026 sector contractions: manufacturing \u22121.5%, professional/scientific/technical \u22126.1%, transportation/storage \u22121.8%",
    "Russian government downgraded 2026 full-year GDP forecast to 0.4% from earlier 1.3%",
    "CBR (June 2026 survey) maintains 2026 GDP growth range at 0.5%\u20131.5% and 2027 at 1.5%\u20132.5%",
    "BOFIT: core-sector index rebounded to ~+2% YoY in Mar\u2013Apr 2026 after ~\u22123% in Jan\u2013Feb; ministry estimated ~1.3% YoY GDP growth in April 2026",
    "Rosstat revised earlier years upward: 2024 to +4.9% and 2023 to +4.1%",
    "Slowdown drivers: military spending priority, low oil prices, weaker gas exports, muted China trade, strong ruble from high interest rates"
  ],
  "data_points": [
    {
      "metric": "Russia real GDP growth, Q1 2026 (YoY)",
      "value": -0.2,
      "unit": "%",
      "as_of": "2026-03-31",
      "source_url": "https://tradingeconomics.com/russia/gdp-growth-annual/news/551263"
    },
    {
      "metric": "Russia real GDP growth, Q4 2025 (YoY, implied by full-year)",
      "value": 1.0,
      "unit": "%",
      "as_of": "2025-12-31",
      "source_url": "https://tradingeconomics.com/russia/gdp-growth-annual/news/551263"
    },
    {
      "metric": "Russia real GDP growth, Q3 2025 (YoY)",
      "value": 0.6,
      "unit": "%",
      "as_of": "2025-09-30",
      "source_url": "https://tradingeconomics.com/russia/gdp-growth-annual/news/509655"
    },
    {
      "metric": "Russia real GDP growth, Q2 2025 (YoY, preliminary)",
      "value": 1.1,
      "unit": "%",
      "as_of": "2025-06-30",
      "source_url": "https://tass.com/economy/2001933"
    },
    {
      "metric": "Russia real GDP growth, H1 2025 (YoY)",
      "value": 1.2,
      "unit": "%",
      "as_of": "2025-06-30",
      "source_url": "https://tass.com/economy/2023817"
    },
    {
      "metric": "Russia real GDP growth, Q1 2025 (YoY, confirmed)",
      "value": 1.4,
      "unit": "%",
      "as_of": "2025-03-31",
      "source_url": "https://tradingeconomics.com/russia/gdp-growth-annual/news/463949"
    },
    {
      "metric": "Russia real GDP growth, full-year 2025",
      "value": 1.0,
      "unit": "%",
      "as_of": "2025-12-31",
      "source_url": "https://interfax.com/newsroom/top-stories/117073/"
    },
    {
      "metric": "Russia real GDP growth, full-year 2024 (revised)",
      "value": 4.9,
      "unit": "%",
      "as_of": "2024-12-31",
      "source_url": "https://en.thebell.io/gdp-data-what-it-reveals-what-it-conceals/"
    },
    {
      "metric": "Russia real GDP growth, full-year 2023 (revised)",
      "value": 4.1,
      "unit": "%",
      "as_of": "2023-12-31",
      "source_url": "https://en.thebell.io/gdp-data-what-it-reveals-what-it-conceals/"
    },
    {
      "metric": "Russia manufacturing output, Q1 2026 (YoY)",
      "value": -1.5,
      "unit": "%",
      "as_of": "2026-03-31",
      "source_url": "https://tradingeconomics.com/russia/gdp-growth-annual"
    },
    {
      "metric": "Russia professional/scientific/technical activities, Q1 2026 (YoY)",
      "value": -6.1,
      "unit": "%",
      "as_of": "2026-03-31",
      "source_url": "https://tradingeconomics.com/russia/gdp-growth-annual"
    },
    {
      "metric": "Russia transportation and storage, Q1 2026 (YoY)",
      "value": -1.8,
      "unit": "%",
      "as_of": "2026-03-31",
      "source_url": "https://tradingeconomics.com/russia/gdp-growth-annual"
    },
    {
      "metric": "Russian government 2026 full-year GDP growth forecast (downgraded)",
      "value": 0.4,
      "unit": "%",
      "as_of": "2026-05-15",
      "source_url": "https://tradingeconomics.com/russia/gdp-growth-annual/news/551263"
    },
    {
      "metric": "Russia economy ministry estimate, April 2026 GDP growth (YoY)",
      "value": 1.3,
      "unit": "%",
      "as_of": "2026-04-30",
      "source_url": "https://www.bofit.fi/en/monitoring/weekly/2026/vw202623_1/"
    }
  ],
  "created_at": "2026-07-07T09:11:15.462193Z",
  "updated_at": "2026-07-08T01:45:52.727758Z",
  "stale_after": "2026-07-08T07:45:52.727758Z",
  "resolvable_after": null,
  "state": "fresh",
  "superseded_by": null,
  "revision_history": [],
  "session_id": "67550a0a-af42-4167-acc4-0363059fd6ff",
  "follow_up_count": 0
}