{
  "slug": "spacex-falcon-9-launch-schedule-june-2026-upcoming-48e1552b",
  "query": "SpaceX Falcon 9 launch schedule June 2026, upcoming launches",
  "answer": "I now have comprehensive data. Here is my full synthesis:\n\n---\n\n# SpaceX Falcon 9 Launch Schedule — June 2026 & Upcoming\n\n## Overview\n\nAs of June 6, 2026, SpaceX has already completed **65 Falcon 9/Falcon Heavy launches** in 2026 (January 1 – June 6), maintaining a remarkable cadence of approximately **one launch every 2.4 days** (~12.7 launches/month). There are **15 Falcon launches listed for June 2026** and **117 additional Falcon missions** manifested from July 2026 onward.\n\n## Recent Completed Launches (Late May – Early June 2026)\n\n| Date | Mission | Pad | Status |\n|------|---------|-----|--------|\n| Jun 4, 2026 | Starlink Group 10-43 | SLC-40, Cape Canaveral | ✅ Success |\n| Jun 3, 2026 | Starlink Group 17-47 | SLC-4E, Vandenberg | ✅ Success |\n| May 30, 2026 | Starlink Group 17-41 | SLC-4E, Vandenberg | ✅ Success |\n| May 29, 2026 | Starlink Group 10-53 | SLC-40, Cape Canaveral | ✅ Success |\n| May 26, 2026 | Starlink Group 17-37 | SLC-4E, Vandenberg | ✅ Success |\n| May 25, 2026 | Starlink Group 10-47 | SLC-40, Cape Canaveral | ✅ Success |\n| May 21, 2026 | Starlink Group 10-31 | SLC-40, Cape Canaveral | ✅ Success |\n| May 20, 2026 | Starlink Group 17-42 | SLC-4E, Vandenberg | ✅ Success |\n| May 15, 2026 | Dragon CRS-2 SpX-34 | SLC-40, Cape Canaveral | ✅ Success |\n| May 12, 2026 | NROL-172 | SLC-4E, Vandenberg | ✅ Success |\n\n## Upcoming June 2026 Launches — Confirmed Dates (\"Go for Launch\")\n\n| Date (UTC) | Mission | Satellites | Pad | Orbit |\n|------------|---------|------------|-----|-------|\n| Jun 7, 02:00 | **Starlink Group 17-43** | 21 Starlink + 2 Starshield | SLC-4E, Vandenberg | LEO |\n| Jun 8, 10:07 | **Starlink Group 10-35** | 29 Starlink | SLC-40, Cape Canaveral | LEO |\n| Jun 10, 14:00 | **Starlink Group 17-44** | 24 Starlink | SLC-4E, Vandenberg | LEO |\n| Jun 12, 12:27 | **Starlink Group 10-54** | 29 Starlink | SLC-40, Cape Canaveral | LEO |\n| Jun 14, 14:00 | **Starlink Group 17-54** | 24 Starlink | SLC-4E, Vandenberg | LEO |\n\n## June 2026 — \"To Be Determined\" (date TBD, listed as June 30 placeholder)\n\n| Mission | Customer | Pad | Orbit |\n|---------|----------|-----|-------|\n| **BlueBird Block 2 #3-5** | AST SpaceMobile | SLC-40, Cape Canaveral | LEO |\n| **Globalstar 2-R Mission 1 (x9)** | Globalstar | SLC-40, Cape Canaveral | LEO |\n| **SDA Tranche 1 Tracking Layer A** | US Space Force/SDA | SLC-4E, Vandenberg | Polar |\n| **SDA Tranche 1 Tracking Layer C** | US Space Force/SDA | SLC-4E, Vandenberg | Polar |\n| **SDA Tranche 1 Tracking Layer E** | US Space Force/SDA | SLC-4E, Vandenberg | Polar |\n| **SDA Tranche 1 Transport Layer A** | US Space Force/SDA | SLC-4E, Vandenberg | Polar |\n| **SDA Tranche 1 Transport Layer D** | US Space Force/SDA | SLC-4E, Vandenberg | Polar |\n| **SDA Tranche 1 Transport Layer E** | US Space Force/SDA | SLC-4E, Vandenberg | Polar |\n| **SDA Tranche 1 Transport Layer F** | US Space Force/SDA | SLC-4E, Vandenberg | Polar |\n| **Sirius SXM-11** | SiriusXM | SLC-40, Cape Canaveral | GTO |\n\n> **Note:** Many of the TBD missions (especially the seven SDA missions) may slip into later months. The June 30 date is a placeholder indicating \"sometime in June or later.\"\n\n## Key Upcoming Missions Beyond June 2026\n\n| Target Date | Mission | Vehicle | Details |\n|-------------|---------|---------|---------|\n| Jul 2026 | **BlueBird Block 2 #6-8** | Falcon 9 | AST SpaceMobile (LEO) |\n| Jul 2026 | **Transporter 17** | Falcon 9 | Rideshare to SSO |\n| Aug 2026 | **Nancy Grace Roman Space Telescope** | **Falcon Heavy** | NASA flagship telescope to Sun-Earth L2 |\n| Aug 2026 | **Dragon CRS-2 SpX-35** | Falcon 9 | ISS resupply |\n| Sep 2026 | **Crew-13** | Falcon 9 | ISS crew rotation |\n| Sep 2026 | **O3b mPower 11-13** | Falcon 9 | SES satellites (MEO) |\n| Nov 2026 | **Griffin Mission One** | **Falcon Heavy** | Astrobotic lunar lander |\n| Dec 2026 | **Blue Ghost Lunar Lander Mission 2** | Falcon 9 | Firefly lunar mission |\n| Dec 2026 | **Nova-C IM-3** | Falcon 9 | Intuitive Machines lunar mission |\n| Dec 2026 | **Telesat Lightspeed 1** | Falcon 9 | LEO broadband constellation |\n\n## Launch Cadence & Statistics\n\n- **65 Falcon launches completed** in 2026 through June 6 (156 days)\n- **Average cadence: 1 launch every 2.4 days** (~12.7/month)\n- **Two active pads** for Falcon 9: SLC-40 (Cape Canaveral) and SLC-4E (Vandenberg), with LC-39A used for Falcon Heavy\n- **Alternating pattern**: SpaceX is alternating between East Coast (Group 10-xx) and West Coast (Group 17-xx) Starlink launches roughly every 2-3 days\n- **117 additional Falcon missions** manifested from July 2026 onward (many with placeholder dates)\n- Dominant payload: Starlink constellation deployment continues to drive the majority of launches\n\n## Data Sources\n\nAll data retrieved from **The Space Devs Launch Library 2 API** (`ll.thespacedevs.com/2.2.0/`) and cross-validated with **RocketLaunch.Live API** (`fdo.rocketlaunch.live`), accessed June 6, 2026.\n\n---",
  "sources": [
    {
      "url": "https://ll.thespacedevs.com/2.2.0/launch/upcoming/?search=falcon",
      "title": "The Space Devs Launch Library 2 API - Upcoming Falcon Launches",
      "domain": "ll.thespacedevs.com",
      "accessed_at": "2026-06-06T00:00:00Z",
      "snippet": "API providing upcoming launch data including dates, pads, missions, and status for all Falcon 9 and Falcon Heavy launches."
    },
    {
      "url": "https://ll.thespacedevs.com/2.2.0/launch/previous/?search=falcon",
      "title": "The Space Devs Launch Library 2 API - Previous Falcon Launches",
      "domain": "ll.thespacedevs.com",
      "accessed_at": "2026-06-06T00:00:00Z",
      "snippet": "API providing historical launch data for completed Falcon 9 missions."
    },
    {
      "url": "https://fdo.rocketlaunch.live/json/launches/next/10",
      "title": "RocketLaunch.Live API - Next 10 Launches",
      "domain": "fdo.rocketlaunch.live",
      "accessed_at": "2026-06-06T00:00:00Z",
      "snippet": "Cross-validation source confirming upcoming Falcon 9 launch dates and details."
    }
  ],
  "key_facts": [
    "SpaceX has completed 65 Falcon 9/Heavy launches in 2026 (Jan 1 – Jun 6), averaging one launch every 2.4 days (~12.7 per month).",
    "Five Falcon 9 launches are confirmed 'Go for Launch' in the next week: Starlink 17-43 (Jun 7), Starlink 10-35 (Jun 8), Starlink 17-44 (Jun 10), Starlink 10-54 (Jun 12), and Starlink 17-54 (Jun 14).",
    "15 total Falcon launches are listed for June 2026, including 5 with firm dates and 10 with TBD/placeholder dates (Jun 30).",
    "TBD June missions include: BlueBird Block 2 #3-5 (AST SpaceMobile), Globalstar 2-R Mission 1, seven SDA Tranche 1 missions, and Sirius SXM-11.",
    "Starlink Group 17-43 (Jun 7) will carry 21 Starlink satellites plus 2 US military Starshield satellites.",
    "SpaceX alternates launches between SLC-40 (Cape Canaveral, FL) and SLC-4E (Vandenberg, CA) every 2-3 days.",
    "117 additional Falcon missions are manifested from July 2026 onward.",
    "Key upcoming high-profile missions: Nancy Grace Roman Space Telescope (Falcon Heavy, Aug 2026), Crew-13 (Sep 2026), Griffin Mission One lunar lander (Falcon Heavy, Nov 2026).",
    "Most recent completed launches: Starlink 10-43 (Jun 4) and Starlink 17-47 (Jun 3), both successful.",
    "Dragon CRS-2 SpX-34 ISS resupply mission launched successfully on May 15, 2026."
  ],
  "data_points": [
    {
      "metric": "Falcon 9/Heavy launches completed in 2026 (Jan 1 – Jun 6)",
      "value": 65.0,
      "unit": "launches",
      "as_of": "2026-06-06",
      "source_url": "https://ll.thespacedevs.com/2.2.0/launch/?search=falcon&net__gte=2026-01-01&net__lte=2026-06-06"
    },
    {
      "metric": "Average launch cadence (days between launches)",
      "value": 2.4,
      "unit": "days per launch",
      "as_of": "2026-06-06",
      "source_url": "https://ll.thespacedevs.com/2.2.0/launch/?search=falcon&net__gte=2026-01-01&net__lte=2026-06-06"
    },
    {
      "metric": "Approximate monthly Falcon launch rate",
      "value": 12.7,
      "unit": "launches per month",
      "as_of": "2026-06-06",
      "source_url": "https://ll.thespacedevs.com/2.2.0/launch/?search=falcon&net__gte=2026-01-01&net__lte=2026-06-06"
    },
    {
      "metric": "Falcon launches listed for June 2026",
      "value": 15.0,
      "unit": "launches",
      "as_of": "2026-06-06",
      "source_url": "https://ll.thespacedevs.com/2.2.0/launch/upcoming/?search=falcon&net__gte=2026-06-01&net__lte=2026-06-30"
    },
    {
      "metric": "Falcon launches with confirmed Go for Launch status in June 2026",
      "value": 5.0,
      "unit": "launches",
      "as_of": "2026-06-06",
      "source_url": "https://ll.thespacedevs.com/2.2.0/launch/upcoming/?search=falcon&net__gte=2026-06-01&net__lte=2026-06-30"
    },
    {
      "metric": "Falcon missions manifested from July 2026 onward",
      "value": 117.0,
      "unit": "launches",
      "as_of": "2026-06-06",
      "source_url": "https://ll.thespacedevs.com/2.2.0/launch/upcoming/?search=falcon&net__gte=2026-07-01"
    },
    {
      "metric": "Starlink satellites on Starlink Group 17-43 (Jun 7)",
      "value": 21.0,
      "unit": "satellites",
      "as_of": "2026-06-06",
      "source_url": "https://ll.thespacedevs.com/2.2.0/launch/upcoming/?search=falcon"
    },
    {
      "metric": "Starshield satellites on Starlink Group 17-43 (Jun 7)",
      "value": 2.0,
      "unit": "satellites",
      "as_of": "2026-06-06",
      "source_url": "https://ll.thespacedevs.com/2.2.0/launch/upcoming/?search=falcon"
    },
    {
      "metric": "Starlink satellites on Starlink Group 10-35 (Jun 8)",
      "value": 29.0,
      "unit": "satellites",
      "as_of": "2026-06-06",
      "source_url": "https://ll.thespacedevs.com/2.2.0/launch/upcoming/?search=falcon"
    }
  ],
  "created_at": "2026-06-06T02:31:45.558900Z",
  "updated_at": "2026-06-06T02:31:45.558900Z",
  "stale_after": "2026-06-06T08:31:45.558900Z",
  "resolvable_after": null,
  "state": "fresh",
  "superseded_by": null,
  "revision_history": [],
  "session_id": "82f0c103-7b2a-41b4-b05f-aa607b59a01c",
  "follow_up_count": 0
}